MANIFEST.in
README.md
setup.py
pbdc/__init__.py
pbdc/pbdc.py
pbdc.egg-info/PKG-INFO
pbdc.egg-info/SOURCES.txt
pbdc.egg-info/dependency_links.txt
pbdc.egg-info/top_level.txt
pbdc/templates/cex.hpp
pbdc/templates/crpc.h
pbdc/templates/pb2.proto
pbdc/templates/restb.idx.cc
pbdc/templates/restb.idx.h
pbdc/templates/restb.store.cc
pbdc/templates/restb.store.h
pbdc/templates/restb.verify.cc
pbdc/templates/restb.verify.h
pbdc/templates/rpc.cc
pbdc/templates/srpc.h