Metadata-Version: 1.1
Name: pbdc
Version: 0.1.15
Summary: python describe data structure and represent with many tools like C/C++ syntax , proto syntax, json, ...etc
Home-page: https://github.com/jj4jj/pbdc
Author: jj4jj
Author-email: resc@vip.qq.com
License: MIT License
Keywords: protobuf,c++,c,data represent
Platform: UNKNOWN
Requires: Jinja2
